<?xml version="1.0" encoding="UTF-8"?>
<populations>
  <population Name = "Melee Weapons 1C" Load = "Merge">
    <group Name="Items" Load="Merge">
      <object Blueprint="SowReap_Scythe" Weight="15" Number="1"/>
      <object Blueprint="SowReap_Sickle" Weight="10" Number="1"/>
    </group>
  </population>

  <population Name = "Melee Weapons 1R" Load = "Merge">
    <group Name = "Items" Load = "Merge">
      <object Blueprint="SowReap_Scythe1" Weight = "15" Number = "1" />
      <object Blueprint="SowReap_Sickle1" Weight = "10" Number = "1" />
    </group>
  </population>

  <population Name = "Melee Weapons 2C" Load = "Merge">
    <group Name="Items" Load="Merge">
      <object Blueprint="SowReap_Scythe2" Weight = "15" Number = "1"/>
      <object Blueprint="SowReap_Sickle2" Weight="10" Number="1"/>
    </group>
  </population>

  <population Name="Melee Weapons 2R">
    <group Name="Items" Load="Merge">
      <object Weight="10" Number="1" Blueprint="SowReap_HolyScythe" />
    </group>
  </population>

  <population Name = "Melee Weapons 3C" Load = "Merge">
    <group Name="Items" Load="Merge">
      <object Blueprint="SowReap_Scythe3" Weight = "15" Number = "1"/>
      <object Blueprint="SowReap_Sickle3" Weight="10" Number="1"/>      
    </group>
  </population>

  <population Name="Melee Weapons 3R">
    <group Name="Items" Load="Merge">
      <object Weight="20" Number="1" Blueprint="SowReap_HolyScythe" />
    </group>
  </population>

  <population Name = "Melee Weapons 4C" Load = "Merge">
    <group Name="Items" Load="Merge">
      <object Blueprint="SowReap_Scythe4" Weight = "15" Number = "1"/>
      <object Blueprint="SowReap_Sickle4" Weight="10" Number="1"/>
    </group>
  </population>

  <population Name="Melee Weapons 4R">
    <group Name="Items" Load="Merge">
      <object Weight="10" Number="1" Blueprint="SowReap_Bone_Sickle" />
    </group>
  </population>

  <population Name = "Melee Weapons 5C" Load = "Merge">
    <group Name="Items" Load="Merge">
      <object Blueprint="SowReap_Scythe5" Weight = "15" Number = "1"/>
      <object Blueprint="SowReap_Sickle5" Weight="10" Number="1"/>
    </group>
  </population>

  <population Name="Melee Weapons 5R">
    <group Name="Items" Load="Merge">
      <object Weight="10" Number="1" Blueprint="SowReap_SplittingScythe" />
      <object Weight="20" Number="1" Blueprint="SowReap_Bone_Sickle" />
    </group>
  </population>

  <population Name = "Melee Weapons 6C" Load = "Merge">
    <group Name="Items" Load="Merge">
      <object Blueprint="SowReap_Scythe6" Weight = "15" Number = "1"/>
      <object Blueprint="SowReap_Sickle6" Weight="10" Number="1"/>
    </group>
  </population>

  <population Name="Melee Weapons 6R">
    <group Name="Items" Load="Merge">
      <object Weight="20" Number="1" Blueprint="SowReap_SplittingScythe" />
    </group>
  </population>

  <population Name = "Melee Weapons 7C" Load = "Merge">
    <group Name="Items" Load="Merge">
      <object Blueprint="SowReap_Scythe7" Weight = "15" Number = "1"/>
      <object Blueprint="SowReap_Sickle7" Weight="10" Number="1"/>
    </group>
  </population>

  <population Name = "Melee Weapons 8C" Load = "Merge">
    <group Name="Items" Load="Merge">
      <object Blueprint="SowReap_Scythe8" Weight = "15" Number = "1"/>
      <object Blueprint="SowReap_Sickle8" Weight="10" Number="1"/>
    </group>
  </population>

  <population Name = "BaseRelic_SowReap_Scythe1">
    <group Name = "Blueprint" Style = "pickone">
      <object Blueprint = "SowReap_Scythe1" Weight="2"/>
      <object Blueprint = "SowReap_Sickle1" Weight="1"/>
    </group>
  </population>

  <population Name = "BaseRelic_SowReap_Scythe2">
    <group Name = "Blueprint" Style = "pickone">
      <object Blueprint = "SowReap_Scythe2" Weight="2"/>
      <object Blueprint = "SowReap_Sickle2" Weight="1"/>
    </group>
  </population>

  <population Name = "BaseRelic_SowReap_Scythe3">
    <group Name = "Blueprint" Style = "pickone">
      <object Blueprint = "SowReap_Scythe3" Weight="2"/>
      <object Blueprint = "SowReap_Sickle3" Weight="1"/>
    </group>
  </population>

  <population Name = "BaseRelic_SowReap_Scythe4">
    <group Name = "Blueprint" Style = "pickone">
      <object Blueprint = "SowReap_Scythe4" Weight="2"/>
      <object Blueprint = "SowReap_Sickle4" Weight="1"/>
    </group>
  </population>

  <population Name = "BaseRelic_SowReap_Scythe5">
    <group Name = "Blueprint" Style = "pickone">
      <object Blueprint = "SowReap_Scythe5" Weight="2"/>
      <object Blueprint = "SowReap_Sickle5" Weight="1"/>
    </group>
  </population>

  <population Name = "BaseRelic_SowReap_Scythe6">
    <group Name = "Blueprint" Style = "pickone">
      <object Blueprint = "SowReap_Scythe6" Weight="2"/>
      <object Blueprint = "SowReap_Sickle6" Weight="1"/>
    </group>
  </population>

  <population Name = "BaseRelic_SowReap_Scythe7">
    <group Name = "Blueprint" Style = "pickone">
      <object Blueprint = "SowReap_Scythe7" Weight="2"/>
      <object Blueprint = "SowReap_Sickle7" Weight="1"/>
    </group>
  </population>

  <population Name = "BaseRelic_SowReap_Scythe8">
    <group Name = "Blueprint" Style = "pickone">
      <object Blueprint = "SowReap_Scythe8" Weight="2"/>
      <object Blueprint = "SowReap_Sickle8" Weight="1"/>
    </group>
  </population>

  <population Name = "SowReap_StartingGear_ScytheFarmer">
    <group Name="Items" Style="pickeach">
      <table Name="StartingGear_Common" />
      <object Blueprint="HalfFullWaterskin" Number="1" />
      <object Blueprint="Vinewafer Sheaf" Number="8-10" />
      <object Blueprint="SowReap_Sickle1" Number="1" />
      <object Blueprint="Woven Tunic" Number="1" />
      <object Blueprint="Farmers Token" Number="1" />         
      <table Name="Ingredients1" Number="2-5" />
      <table Name="Cookbooks" Number="1" />
      <object Blueprint="Witchwood Bark" Number="6-8" />
    </group>
  </population>

</populations>